ch_nn/__init__.py
ch_nn/self_frame.py
ch_nn-1.0.0.dist-info/LICENSE
ch_nn-1.0.0.dist-info/METADATA
ch_nn-1.0.0.dist-info/WHEEL
ch_nn-1.0.0.dist-info/top_level.txt
ch_nn-1.0.0.dist-info/RECORD
