Metadata-Version: 2.1
Name: ch-nn
Version: 1.0.0
Summary: This is a simple but function completed neural networks framework
Home-page: https://github.com/KINGSEIY/build_neural_framework_by_hand
Author: CH Wong
Author-email: wchh81@gmail.com
License: UNKNOWN
Platform: UNKNOWN
Classifier: Programming Language :: Python :: 3
Classifier: License :: OSI Approved :: MIT License
Classifier: Operating System :: OS Independent
Requires-Python: >=3.6
